{
  "schema": 1,
  "name": "bot-rxts",
  "first_seen": 1778288413.6713269,
  "last_seen": 1778293686.83275,
  "episodes": 150,
  "score_total": 722,
  "score_best": 30,
  "best_loadout": [
    1,
    1,
    1,
    1,
    1
  ],
  "killed_by": {
    "Soldier Ant": 1,
    "Scorpion": 2,
    "Cactus": 4,
    "bot-vtbg": 1,
    "bot-gpyo": 1,
    "bot-ngro": 1,
    "Beetle": 8,
    "Hornet": 62,
    "bot-xhjd": 1,
    "bot-ldav": 2,
    "root": 4,
    "Bee": 10,
    "Rock": 2,
    "bot-gfyw": 4,
    "bot-fjcn": 1,
    "leafy": 3,
    "bot-nfns": 1,
    "Centipede": 3,
    "bot-lovo": 3,
    "bot-nvzr": 4,
    "bot-rvnt": 1,
    "bot-hxft": 2,
    "Massive Beetle": 1,
    "aa": 1,
    "bot-byku": 2,
    "bot-shdk": 1,
    "bot-qbze": 3,
    "bot-eamp": 2,
    "bot-eekg": 1,
    "bot-dspg": 1,
    "Spider": 1,
    "bot-jryz": 1,
    "bot-tlpa": 1,
    "bot-fdea": 1,
    "bot-osln": 1,
    "bot-pabq": 3,
    "bot-apgp": 1
  },
  "loadout_history": {
    "0": 8,
    "1": 149,
    "32": 1,
    "42": 1
  }
}