{
  "schema": 1,
  "name": "bot-603",
  "first_seen": 1778364748.675509,
  "last_seen": 1778470884.328181,
  "episodes": 88,
  "score_total": 1094,
  "score_best": 72,
  "best_loadout": [
    0,
    0,
    0,
    0,
    0
  ],
  "killed_by": {
    "Hornet": 32,
    "Evil Centipede": 2,
    "Beetle": 9,
    "Worker Ant": 1,
    "bot-704": 2,
    "Soldier Ant": 7,
    "Bee": 3,
    "bot-404": 4,
    "Massive Beetle": 2,
    "Spider": 3,
    "bot-301": 1,
    "bot-212": 3,
    "Cactus": 5,
    "Centipede": 3,
    "bot-703": 1,
    "bot-107": 1
  },
  "loadout_history": {
    "0": 80,
    "1": 72,
    "18": 3,
    "7": 1,
    "34": 1,
    "19": 1,
    "79": 1,
    "8": 1,
    "28": 1
  }
}