{
  "schema": 1,
  "name": "bot-502",
  "first_seen": 1778364747.952054,
  "last_seen": 1778542956.023747,
  "episodes": 92,
  "score_total": 1240,
  "score_best": 72,
  "best_loadout": [
    0,
    24,
    10,
    0,
    0
  ],
  "killed_by": {
    "Hornet": 42,
    "Spider": 2,
    "Cactus": 8,
    "Massive Beetle": 3,
    "Beetle": 9,
    "Sandstorm": 1,
    "Ant Hole": 4,
    "Worker Ant": 3,
    "blossom": 1,
    "Evil Centipede": 1,
    "bot-208": 1,
    "Soldier Ant": 4,
    "bot-501": 1,
    "bot-405": 1,
    "Bee": 1,
    "Wasp": 2
  },
  "loadout_history": {
    "0": 85,
    "1": 65,
    "10": 2,
    "49": 2,
    "50": 1,
    "28": 1,
    "11": 2,
    "25": 1,
    "9": 1,
    "24": 2
  }
}