{
  "schema": 1,
  "name": "bot-131",
  "first_seen": 1778543543.0287948,
  "last_seen": 1778638532.490131,
  "episodes": 594,
  "score_total": 117600,
  "score_best": 5307,
  "best_loadout": [
    0,
    0,
    0,
    0,
    0,
    0,
    0
  ],
  "killed_by": {
    "bot-29": 2,
    "Hornet": 141,
    "Mantis": 47,
    "Beetle": 35,
    "Evil Centipede": 8,
    "Cactus": 37,
    "bot-138": 1,
    "Spider": 17,
    "bot-139": 1,
    "bot-80": 2,
    "Wasp": 91,
    "Centipede": 18,
    "bot-71": 1,
    "Bee": 43,
    "bot-51": 1,
    "Rock": 4,
    "Worker Ant": 6,
    "Scorpion": 4,
    "bot-37": 1,
    "bot-74": 1,
    "Ladybug": 22,
    "Leafbug": 11,
    "Bush": 4,
    "bot-93": 1,
    "bot-27": 3,
    "bot-127": 1,
    "bot-116": 1,
    "67": 4,
    "bot-135": 1,
    "bot-104": 2,
    "Soldier Ant": 3,
    "Sandstorm": 5,
    "bot-55": 1,
    "flower": 1,
    "bot-144": 3,
    "bot-47": 2,
    "bot-72": 1,
    "bot-44": 1,
    "blossom": 3,
    "bot-109": 2,
    "bot-35": 1,
    "bot-61": 3,
    "not bot": 1,
    "bot-66": 1,
    "bot-68": 1,
    "Desert Centipede": 3,
    "bot-33": 1,
    "bot-106": 1,
    "thorny": 1,
    "bot-108": 1,
    "bot-53": 3,
    "bot-96": 1,
    "bot-134": 1,
    "hello": 1,
    "bot-40": 1,
    "bot-32": 1,
    "bot-84": 2,
    "bot-148": 2,
    "bot-34": 1,
    "bot-136": 5,
    "bot-92": 1,
    "bot-137": 2,
    "bot-98": 1,
    "bot-112": 2,
    "bot-82": 1,
    "bot-76": 1,
    "aa": 1,
    "blossom-v2": 1,
    "bot-126": 1,
    "bot-45": 1,
    "petalpop": 2,
    "bot-41": 2,
    "bot-63": 1,
    "Baby Ant": 1,
    "bot-87": 1,
    "bot-78": 3
  },
  "loadout_history": {
    "0": 490,
    "1": 413,
    "5": 11,
    "14": 11,
    "15": 11,
    "31": 2,
    "10": 3,
    "33": 4,
    "9": 6,
    "7": 2,
    "25": 6,
    "6": 6,
    "19": 3,
    "116": 3,
    "18": 3,
    "26": 1,
    "60": 1,
    "35": 1,
    "167": 2,
    "24": 2,
    "117": 1,
    "8": 2,
    "20": 1,
    "69": 1,
    "64": 1,
    "16": 1,
    "84": 1,
    "48": 1,
    "11": 1,
    "13": 1,
    "79": 1,
    "182": 1,
    "61": 1
  }
}