{
  "schema": 1,
  "name": "bot-myzm",
  "first_seen": 1778288413.7646809,
  "last_seen": 1778293683.754695,
  "episodes": 148,
  "score_total": 861,
  "score_best": 40,
  "best_loadout": [
    1,
    1,
    1,
    1,
    1
  ],
  "killed_by": {
    "Hornet": 78,
    "Cactus": 2,
    "bot-jxut": 1,
    "bot-krwp": 1,
    "bot-cplq": 6,
    "bot-pksx": 1,
    "bot-yjlg": 1,
    "bot-gdpr": 2,
    "Evil Centipede": 4,
    "bot-yqmx": 2,
    "bot-pabq": 2,
    "bot-ldav": 1,
    "67": 3,
    "bot-ijcq": 1,
    "bot-muhi": 1,
    "bot-zazb": 2,
    "Bee": 4,
    "Rock": 1,
    "rosie": 3,
    "bot-vtbg": 1,
    "Centipede": 2,
    "bot-ftfi": 1,
    "Ladybug": 1,
    "Spider": 1,
    "bot-fksq": 2,
    "root": 4,
    "bot-gdrg": 4,
    "Beetle": 2,
    "Worker Ant": 1,
    "bot-shdk": 1,
    "Sandstorm": 1,
    "bot-slua": 2,
    "bot-ephv": 1,
    "bot-jwhw": 1,
    "bot-sadh": 1
  },
  "loadout_history": {
    "1": 147,
    "14": 1,
    "0": 6
  }
}