{
  "schema": 1,
  "name": "bot-70",
  "first_seen": 1778543504.171948,
  "last_seen": 1778713155.7765398,
  "episodes": 1183,
  "score_total": 178504,
  "score_best": 5332,
  "best_loadout": [
    0,
    0,
    0,
    0,
    10,
    0,
    0
  ],
  "killed_by": {
    "Hornet": 288,
    "blossom-v2": 3,
    "bot-94": 1,
    "Wasp": 227,
    "Ladybug": 49,
    "Desert Centipede": 5,
    "bot-36": 3,
    "Bee": 75,
    "bot-141": 1,
    "Beetle": 39,
    "Evil Centipede": 16,
    "bot-54": 1,
    "bot-30": 5,
    "Sandstorm": 16,
    "Mantis": 105,
    "Centipede": 23,
    "Spider": 56,
    "Cactus": 76,
    "bot-37": 1,
    "Scorpion": 5,
    "bot-88": 1,
    "bot-51": 1,
    "Rock": 15,
    "zorr": 8,
    "Leafbug": 28,
    "bot-136": 2,
    "bot-101": 3,
    "bot-58": 1,
    "bot-102": 1,
    "bot-27": 2,
    "Baby Ant": 2,
    "Bush": 10,
    "bot-68": 3,
    "bot-125": 1,
    "prickly": 2,
    "bot-90": 1,
    "bot-124": 3,
    "bot-69": 2,
    "not bot": 5,
    "bot-116": 5,
    "bot-62": 2,
    "thorn": 1,
    "bot-42": 2,
    "bot-52": 1,
    "bot-60": 1,
    "hello": 1,
    "bot-74": 1,
    "bot-121": 1,
    "bot-24": 4,
    "bot-83": 2,
    "bot-132": 1,
    "bot-81": 1,
    "bot-67": 1,
    "bot-25": 1,
    "bot-142": 2,
    "Soldier Ant": 1,
    "bot-105": 1,
    "bot-104": 2,
    "bot-34": 1,
    "bloom": 1,
    "bot-38": 1,
    "blossom": 3,
    "bot-133": 2,
    "bot-46": 1,
    "bot-149": 2,
    "bloomy": 1,
    "leafy": 2,
    "bot-82": 1,
    "florrio": 1,
    "bot-84": 3,
    "bot-91": 1,
    "bot-50": 5,
    "bot-22": 2,
    "bot-86": 2,
    "67": 1,
    "bot-148": 1,
    "bot-140": 1,
    "bot-145": 1,
    "bot-76": 1,
    "bot-99": 1,
    "bot-53": 1,
    "bot-130": 1,
    "Worker Ant": 1,
    "bot-39": 1,
    "bot-40": 1,
    "bot": 1,
    "bot-122": 1,
    "bot-75": 2,
    "bot-45": 2,
    "bot-32": 1,
    "bot-118": 1,
    "bot-106": 1,
    "aa": 1,
    "bot-73": 1,
    "gardn": 2,
    "bot-61": 1,
    "bot-23": 1,
    "bot-147": 1,
    "bot-55": 1
  },
  "loadout_history": {
    "0": 998,
    "1": 819,
    "18": 4,
    "10": 5,
    "5": 8,
    "7": 2,
    "15": 8,
    "9": 10,
    "14": 10,
    "51": 3,
    "29": 5,
    "6": 8,
    "167": 2,
    "45": 1,
    "116": 4,
    "26": 2,
    "35": 7,
    "20": 4,
    "83": 1,
    "64": 1,
    "21": 2,
    "32": 1,
    "79": 2,
    "24": 6,
    "19": 4,
    "207": 1,
    "60": 2,
    "8": 2,
    "46": 3,
    "58": 1,
    "28": 2,
    "181": 1,
    "25": 3,
    "23": 1,
    "13": 1,
    "12": 1,
    "30": 1,
    "16": 1,
    "123": 1
  }
}